[
    {
        "name": "Happy Cat Care",
        "time": 3,
        "overview1": "A complete pet service website with firebase authentication.",
        "overview2": "Dashboard Feature, with admin privilege to add & manage services",
        "overview3": "Different nested route for different users & add review system.",
        "clientLink": "https://github.com/kbnul001/happy-cat-care-client",
        "serverLink": "https://github.com/kbnul001/happy-cat-care-server",
        "liveLink": "https://happy-cat-care.web.app/",
        "img": "https://i.ibb.co/f1NKFZv/happycat.jpg",
        "technology": "React, Material UI, Firebase, Express, React Router"
    },
    {
        "name": "Impel Tourism",
        "time": 3,
        "overview1": "A Tourism Website with Firebase authentication system",
        "overview2": "Add more destinations with a form and mobile responsive",
        "overview3": "Manage all orders, my orders, change status to approves from pending",
        "clientLink": "https://github.com/kbnul001/Impel-tourism",
        "serverLink": "https://github.com/kbnul001/impel-tourism-server",
        "liveLink": "https://impel-tourism.web.app/",
        "img": "https://i.ibb.co/Ntzx9Rs/tourism.jpg",
        "technology": "React, Tailwind, Firebase, Express, React Router"
    },
    {
        "name": "Impel Health Care",
        "time": 2,
        "overview1": "A Health Care Related Site with Google, Github & Email Sing in.",
        "overview2": "Private/ Protected Route system.",
        "overview3": "Dynamic Route System and fully responsive website.",
        "clientLink": "https://github.com/kbnul001/Impel-health-care",
        "liveLink": "https://impel-health-care.web.app/",
        "img": "https://i.ibb.co/tKYp9yB/impelhealthmobile.jpg",
        "technology": "React, Tailwind, Firebase React Router, React Hook"
    }
]